sshadb/__init__.py
sshadb/client.py
sshadb/exceptions.py
sshadb/py.typed
sshadb/commands/__init__.py
sshadb/commands/devices.py
sshadb/commands/get_state.py
sshadb/commands/pull.py
sshadb/commands/push.py
sshadb/commands/shell.py
sshadb/core/__init__.py
sshadb/core/adb_executor.py
sshadb/core/file_transfer.py
sshadb/core/ssh_client.py
sshadb/utils/__init__.py
sshadb/utils/parser.py
sshadb-0.1.0.dist-info/licenses/LICENSE
sshadb-0.1.0.dist-info/METADATA
sshadb-0.1.0.dist-info/WHEEL
sshadb-0.1.0.dist-info/top_level.txt
sshadb-0.1.0.dist-info/RECORD
