Metadata-Version: 2.4
Name: sshadb
Version: 0.1.0
Summary: Run Android ADB over SSH on a remote host with a simple Python API
License: MIT License
Project-URL: Homepage, https://github.com/dhkimxx/sshadb
Keywords: adb,android,ssh,remote,paramiko
Classifier: Development Status :: 3 - Alpha
Classifier: Intended Audience :: Developers
Classifier: License :: OSI Approved :: MIT License
Classifier: Programming Language :: Python :: 3
Classifier: Programming Language :: Python :: 3 :: Only
Classifier: Programming Language :: Python :: 3.11
Classifier: Operating System :: OS Independent
Classifier: Typing :: Typed
Requires-Python: >=3.11
License-File: LICENSE
Requires-Dist: paramiko<4,>=3.3
Provides-Extra: test
Requires-Dist: pytest>=7.4; extra == "test"
Requires-Dist: pytest-cov>=4; extra == "test"
Requires-Dist: python-dotenv>=1.0; extra == "test"
Provides-Extra: dev
Requires-Dist: pytest>=7.4; extra == "dev"
Requires-Dist: pytest-cov>=4; extra == "dev"
Requires-Dist: ruff>=0.6; extra == "dev"
Requires-Dist: mypy>=1.10; extra == "dev"
Requires-Dist: python-dotenv>=1.0; extra == "dev"
Dynamic: license-file
